d2b/__init__.py
d2b/cli.py
d2b/commands/__init__.py
d2b/commands/run.py
d2b/commands/scaffold.py
d2b/commands/scaffold_template/.bidsignore
d2b/commands/scaffold_template/CHANGES
d2b/commands/scaffold_template/README
d2b/commands/scaffold_template/participants.json
d2b/commands/scaffold_template/participants.tsv
d2b/d2b.py
d2b/defaults.py
d2b/hookspecs.py
d2b/internal_plugins/__init__.py
d2b/internal_plugins/core.py
d2b/plugins.py
d2b/scaffold.py
d2b/utils.py
d2b-1.4.2.dist-info/entry_points.txt
d2b-1.4.2.dist-info/LICENSE
d2b-1.4.2.dist-info/WHEEL
d2b-1.4.2.dist-info/METADATA
d2b-1.4.2.dist-info/RECORD
