Metadata-Version: 2.1
Name: d2b
Version: 1.4.2
Summary: Organize data in the BIDS format
Home-page: https://github.com/d2b-dev/d2b
Keywords: neuroscience,neuroimaging,bids,cli,tool
Author: Andrew Ross
Author-email: andrew.ross.mail@gmail.com
Requires-Python: >=3.8.0,<4.0
Classifier: Environment :: Console
Classifier: Intended Audience :: Developers
Classifier: Intended Audience :: Healthcare Industry
Classifier: Intended Audience :: Science/Research
Classifier: Operating System :: MacOS
Classifier: Operating System :: Microsoft :: Windows
Classifier: Operating System :: Unix
Classifier: Programming Language :: Python
Classifier: Programming Language :: Python :: 3
Classifier: Programming Language :: Python :: 3.10
Classifier: Programming Language :: Python :: 3.8
Classifier: Programming Language :: Python :: 3.9
Classifier: Topic :: Scientific/Engineering
Classifier: Topic :: Scientific/Engineering :: Bio-Informatics
Classifier: Topic :: Scientific/Engineering :: Medical Science Apps.
Classifier: Topic :: Software Development :: Libraries :: Python Modules
Classifier: Topic :: Utilities
Classifier: Typing :: Typed
Requires-Dist: pluggy (>=0.12,<1.0.0a1)
Project-URL: Documentation, https://github.com/d2b-dev/d2b
Project-URL: Repository, https://github.com/d2b-dev/d2b
